jupyter_libyt/__init__.py
jupyter_libyt/_version.py
jupyter_libyt/provisioning/__init__.py
jupyter_libyt/provisioning/libyt_kernel_provisioner.py
jupyter_libyt/provisioning/py.typed
jupyter_libyt-0.3.0.data/data/share/jupyter/labextensions/@yt-project/jupyter-libyt/package.json
jupyter_libyt-0.3.0.data/data/share/jupyter/labextensions/@yt-project/jupyter-libyt/schemas/@yt-project/jupyter-libyt/package.json.orig
jupyter_libyt-0.3.0.data/data/share/jupyter/labextensions/@yt-project/jupyter-libyt/schemas/@yt-project/jupyter-libyt/plugin.json
jupyter_libyt-0.3.0.data/data/share/jupyter/labextensions/@yt-project/jupyter-libyt/static/509.189c172e1b79ed4d2927.js
jupyter_libyt-0.3.0.data/data/share/jupyter/labextensions/@yt-project/jupyter-libyt/static/728.dd9d727454c0bb9ffbd7.js
jupyter_libyt-0.3.0.data/data/share/jupyter/labextensions/@yt-project/jupyter-libyt/static/remoteEntry.39d5772d94a924154ea2.js
jupyter_libyt-0.3.0.data/data/share/jupyter/labextensions/@yt-project/jupyter-libyt/static/style.js
jupyter_libyt-0.3.0.data/data/share/jupyter/labextensions/@yt-project/jupyter-libyt/static/third-party-licenses.json
jupyter_libyt-0.3.0.dist-info/METADATA
jupyter_libyt-0.3.0.dist-info/WHEEL
jupyter_libyt-0.3.0.dist-info/entry_points.txt
jupyter_libyt-0.3.0.dist-info/licenses/AUTHORS.md
jupyter_libyt-0.3.0.dist-info/licenses/LICENSE
jupyter_libyt-0.3.0.dist-info/RECORD
