Metadata-Version: 2.4
Name: jupyter_libyt
Version: 0.3.0
Summary: A Jupyter kernel provisioner for libyt
Project-URL: Homepage, https://github.com/yt-project/jupyter_libyt
Author-email: Shin-Rong Tsai <turquoisea.tsai@gmail.com>
License: BSD 3-Clause License
License-File: AUTHORS.md
License-File: LICENSE
Keywords: jupyter,jupyterlab,jupyterlab-extension,kernel,libyt,libyt_kernel
Classifier: Development Status :: 3 - Alpha
Classifier: Framework :: Jupyter
Classifier: Framework :: Jupyter :: JupyterLab
Classifier: Framework :: Jupyter :: JupyterLab :: 4
Classifier: Framework :: Jupyter :: JupyterLab :: Extensions
Classifier: Framework :: Jupyter :: JupyterLab :: Extensions :: Prebuilt
Classifier: Intended Audience :: Developers
Classifier: Intended Audience :: Science/Research
Classifier: License :: OSI Approved :: BSD License
Classifier: Natural Language :: English
Classifier: Programming Language :: Python :: 3
Requires-Python: >=3.7
Requires-Dist: jupyter-client<9,>=7.0.0
